jazzml/__init__.py
jazzml/jazzml.py
jazzml-0.1.1.dist-info/LICENSE.txt
jazzml-0.1.1.dist-info/METADATA
jazzml-0.1.1.dist-info/WHEEL
jazzml-0.1.1.dist-info/top_level.txt
jazzml-0.1.1.dist-info/RECORD
