Metadata-Version: 2.1
Name: jazzml
Version: 0.1.1
Summary: Decoder for json/yaml documents
Home-page: https://github.com/jcmincke/jazzml
Author: Jean-Christophe Mincke
Author-email: jeanchristophe.mincke@gmail.com
Classifier: Programming Language :: Python :: 3.10
Classifier: License :: OSI Approved :: Mozilla Public License 2.0 (MPL 2.0)
Classifier: Operating System :: OS Independent
License-File: LICENSE.txt
Requires-Dist: PyYAML
